izaber_wamp_zerp-2.9.20260105.dist-info/METADATA
izaber_wamp_zerp-2.9.20260105.dist-info/WHEEL
izaber_wamp_zerp-2.9.20260105.dist-info/entry_points.txt
izaber_wamp_zerp-2.9.20260105.dist-info/licenses/LICENCE.txt
izaber_wamp_zerp/__init__.py
izaber_wamp_zerp/__main__.py
izaber_wamp_zerp/controller.py
izaber_wamp_zerp/generate_types.py
izaber_wamp_zerp/models/__init__.py
izaber_wamp_zerp/models/zerp.py
izaber_wamp_zerp/py.typed
izaber_wamp_zerp/wampcli.py
izaber_wamp_zerp-2.9.20260105.dist-info/RECORD
