Metadata-Version: 2.1
Name: izaber_wamp_zerp
Version: 2.9.20260105
Summary: Base load point for iZaber WAMP ZERP code
Author-Email: Aki Mimoto <aki+izaber@zaber.com>
License: MIT
Project-URL: Homepage, https://github.com/zabertech/python-izaber-wamp-zerp
Project-URL: Download, https://github.com/zabertech/python-izaber-wamp-zerp/archive/2.9.20260105.tar.gz
Requires-Python: <4.0,>=3.8.0
Requires-Dist: pytz
Requires-Dist: izaber-wamp
Requires-Dist: docopt
Requires-Dist: swampyer>=1.20190905
Requires-Dist: tqdm
